{"success":true,"data":{"ocrText":"课程表\n周四 3-4节 数字经济 姚凯老师 颐德楼H212 1-17周\n周五 3-4节 马克思主义基本原理 王姗姗老师 经世楼C406 1-17周\n周三 4-4节 形势与政策III 毛思程老师 经世楼C304 7-13周 单周\n周三 5-6节 创新程序设计实践 陈智老师 颐德楼H303 1-4周\n周三 5-6节 创新程序设计实践 周峰老师 颐德楼H303 5-15周\n周三 5-6节 创新程序设计实践 段江老师 颐德楼H303 16-17周\n周四 5-7节 算法分析与设计 施龙老师 经世楼E302 1-17周\n周五 5-6节 概率论与数理统计B 郭斌,张晨琳老师 经世楼G101 1-17周\n周一 6-7节 概率论与数理统计B 郭斌,张晨琳老师 经世楼G101 1-17周\n周三 7-9节 数字逻辑电路 张蕊老师 颐德楼H101 1-17周\n周五 7-9节 计算机网络 谈进老师 经世楼D104 1-17周\n周四 8-9节 排球3 李铸老师 晨曦排球场1教学区 1-17周\n周二 10-12节 大学物理 林飞老师 颐德楼H103 1-17周\n周四 10-12节 创业基础 买尔旦·阿木提老师 经世楼C204 1-12周","confidence":0.95,"inputHash":"eef5a518fc7817fb3413025161e4f449552a9fedc5ae2a40a33bc500f9403a17","processingTimeMs":424,"source":"PDF","warnings":[],"semesterStart":"2026-09-07"}}